README.md
setup.py
feature_vectors.egg-info/PKG-INFO
feature_vectors.egg-info/SOURCES.txt
feature_vectors.egg-info/dependency_links.txt
feature_vectors.egg-info/requires.txt
feature_vectors.egg-info/top_level.txt
fvecs/__init__.py
fvecs/featurevec.py
fvecs/fv_rulefit.py
fvecs/utils.py